{
    "building": {
        "ID": 145655,
        "BLDG_USE_TYPE": "ACTIVITY",
        "CONDITIONING": "HEATING_AND_COOLING",
        "CONSTRUCTION_TYPE": "NON_RESIDENTIAL",
        "EFFICIENCY_PACKAGE_TYPE": null,
        "HEATING_FUEL_TYPE": null,
        "IS_NONRESIDENTIAL_CONDITIONING": null,
        "IS_RESIDENTIAL_CONDITIONING": null,
        "IS_SEMIHEATED_CONDITIONING": null,
        "PROJECT_TYPE": "ADDITION",
        "SEMIHEATED": 0,
        "efficiencyPackage2Applies": null,
        "efficiencyPackage2Type": null,
        "performanceRating": null
    },
    "user_project": null,
    "location": {
        "ID": 145591,
        "BUILDING_ID": 145655,
        "CITY": "Portland",
        "COUNTY": null,
        "STATE": "Oregon",
        "epwFilename": null
    },
    "control": {
        "ID": 145656,
        "BUILDING_ID": 145655,
        "CODE": "CEZ_OR",
        "COMPLIANCE_MODE": "PRESCRIPTIVE",
        "ENGINE_VERSION": "11.1.0"
    },
    "lighting": {
        "ID": 145597,
        "BUILDING_ID": 145655,
        "EXTERIOR_LIGHTING_ZONE_TYPE": "EXT_ZONE_UNSPECIFIED",
        "building_area_use": null,
        "exterior_use": {
            "0": {
                "ID": 209572,
                "AREA_DESCRIPTION": null,
                "EXTERIOR_TYPE": "EXTERIOR_INVALID_USE",
                "IS_TRADABLE": 0,
                "LIGHTING_ID": 145597,
                "POWER_DENSITY": 0.0,
                "QUANTITY_UNITS": null,
                "USE_QUANTITY": 0.0,
                "exterior_space": null
            }
        }
    },
    "project_info": {
        "ID": 145637,
        "BUILDING_ID": 145655,
        "DEVELOPER_ADDRESS": "1600 NW 167th Pl. Ste. 330",
        "DEVELOPER_ADDRESS2": null,
        "DEVELOPER_CITY": "Beaverton",
        "DEVELOPER_COMPANY": "Alliant Systems",
        "DEVELOPER_EMAIL": "e.stoyan@alliant-systems.com",
        "DEVELOPER_FIRST_NAME": "Eddie",
        "DEVELOPER_LAST_NAME": "Stoyan",
        "DEVELOPER_PHONE": "503-619-4000",
        "DEVELOPER_STATE": "OR",
        "DEVELOPER_ZIP_CODE": "97006",
        "NOTES": null,
        "OWNER_ADDRESS": null,
        "OWNER_ADDRESS2": null,
        "OWNER_CITY": null,
        "OWNER_COMPANY": null,
        "OWNER_EMAIL": null,
        "OWNER_FIRST_NAME": null,
        "OWNER_LAST_NAME": null,
        "OWNER_PHONE": null,
        "OWNER_STATE": null,
        "OWNER_ZIP_CODE": null,
        "PROJECT_ADDRESS": "100 SW Main St.",
        "PROJECT_ADDRESS2": null,
        "PROJECT_CITY": "Portland",
        "PROJECT_COMPLETE": null,
        "PROJECT_LOT_NUMBER": null,
        "PROJECT_PERMIT_DATE": "9/6/12",
        "PROJECT_PERMIT_NUMBER": "12-179684-FA",
        "PROJECT_STATE": "OR",
        "PROJECT_TAX_MAP": null,
        "PROJECT_TITLE": "First & Main - USPS T.I.",
        "PROJECT_ZIP_CODE": null
    },
    "swh_systems": null,
    "envelope": null,
    "hvac": {
        "ID": 73976,
        "BUILDING_ID": 145655,
        "hvac_plants": null,
        "hvac_systems": {
            "0": {
                "ID": 182596,
                "ALT_EXEMPT_TYPE": null,
                "CONDENSER": "NO_CONDENSER",
                "CONST_VOL_MIXING_BOX": 0,
                "COOLING_EQUIPMENT": "HEAT_PUMP_EQUIPMENT",
                "COOLING_EQUIP_CAPACITY": 54.9,
                "DESCRIPTION": "HVAC System 1",
                "DESCRIPTION_COOL_EQUIP": "Cooling",
                "DESCRIPTION_HEAT_EQUIP": "Heating",
                "DISTRIBUTION": "SINGLE_DUCT",
                "ECONOMIZER": "UNKNOWN_ECONOMIZER",
                "ECONOMIZER_EXCEPTION": "UNKNOWN_ECONOMIZER_EXCEPTION",
                "ELECTRIC_REHEAT": 0,
                "FAN_CONTROL": "VANE_AXIAL_FAN_W_VARIABLE_PITCH_BLADES",
                "FAN_POWERED_VAV": 0,
                "FAN_SYSTEM_ID": null,
                "FAN_SYSTEM_KEY": "UNKNOWN_FAN_SYSTEM",
                "FAN_SYSTEM_OBJ_NUM": null,
                "FUEL": "ELECTRIC",
                "HEATING_EQUIPMENT": "HEAT_PUMP",
                "HEATING_EQUIP_CAPACITY": 58.0,
                "HEAT_PUMP": "WATER_LOOP_HEATPUMP",
                "HVAC_ID": 73976,
                "HYDRONIC_REHEAT": 0,
                "IS_HEATING_SYS_WEATHERIZED": null,
                "LIST_POSITION": 5,
                "PERIMETER_SYSTEM": 0,
                "PROP_COOLING_EQUIP_EFFICIENCY": 15.9,
                "PROP_HEATING_EQUIP_EFFICIENCY": 5.0,
                "QUANTITY": 1,
                "QUANTITY_COOL_EQUIP": 1,
                "QUANTITY_HEAT_EQUIP": 1,
                "REHEAT_RECOOL_COIL": 0,
                "RETURN_FAN_HP": 0.0,
                "STEAM_REHEAT": 0,
                "SUPPLY_FAN_HP": 0.0,
                "SUPPLY_STATIC_PRESSURE": 0.08,
                "SYSTEM_TYPE": null,
                "TOTAL_FAN_HP": 0.0,
                "VAR_AIR_BOX": 0,
                "VAR_AIR_VOL_MIXING_BOX": 0,
                "ZONE": "SINGLE_ZONE",
                "fanSystem": null,
                "isHeatingSysWeatherized": null
            },
            "1": {
                "ID": 182597,
                "ALT_EXEMPT_TYPE": null,
                "CONDENSER": "NO_CONDENSER",
                "CONST_VOL_MIXING_BOX": 0,
                "COOLING_EQUIPMENT": "HEAT_PUMP_EQUIPMENT",
                "COOLING_EQUIP_CAPACITY": 31.6,
                "DESCRIPTION": "HVAC System 2",
                "DESCRIPTION_COOL_EQUIP": "Cooling",
                "DESCRIPTION_HEAT_EQUIP": "Heating",
                "DISTRIBUTION": "UNKNOWN_DISTRIBUTION",
                "ECONOMIZER": "UNKNOWN_ECONOMIZER",
                "ECONOMIZER_EXCEPTION": "UNKNOWN_ECONOMIZER_EXCEPTION",
                "ELECTRIC_REHEAT": 0,
                "FAN_CONTROL": "UNKNOWN_FAN_CONTROL",
                "FAN_POWERED_VAV": 0,
                "FAN_SYSTEM_ID": null,
                "FAN_SYSTEM_KEY": "UNKNOWN_FAN_SYSTEM",
                "FAN_SYSTEM_OBJ_NUM": null,
                "FUEL": "ELECTRIC",
                "HEATING_EQUIPMENT": "HEAT_PUMP",
                "HEATING_EQUIP_CAPACITY": 39.3,
                "HEAT_PUMP": "WATER_LOOP_HEATPUMP",
                "HVAC_ID": 73976,
                "HYDRONIC_REHEAT": 0,
                "IS_HEATING_SYS_WEATHERIZED": null,
                "LIST_POSITION": 10,
                "PERIMETER_SYSTEM": 0,
                "PROP_COOLING_EQUIP_EFFICIENCY": 16.0,
                "PROP_HEATING_EQUIP_EFFICIENCY": 5.4,
                "QUANTITY": 1,
                "QUANTITY_COOL_EQUIP": 1,
                "QUANTITY_HEAT_EQUIP": 1,
                "REHEAT_RECOOL_COIL": 0,
                "RETURN_FAN_HP": 0.0,
                "STEAM_REHEAT": 0,
                "SUPPLY_FAN_HP": 0.0,
                "SUPPLY_STATIC_PRESSURE": 0.0,
                "SYSTEM_TYPE": null,
                "TOTAL_FAN_HP": 0.0,
                "VAR_AIR_BOX": 0,
                "VAR_AIR_VOL_MIXING_BOX": 0,
                "ZONE": "SINGLE_ZONE",
                "fanSystem": null,
                "isHeatingSysWeatherized": null
            },
            "2": {
                "ID": 182598,
                "ALT_EXEMPT_TYPE": null,
                "CONDENSER": "NO_CONDENSER",
                "CONST_VOL_MIXING_BOX": 0,
                "COOLING_EQUIPMENT": "HEAT_PUMP_EQUIPMENT",
                "COOLING_EQUIP_CAPACITY": 31.6,
                "DESCRIPTION": "HVAC System 3",
                "DESCRIPTION_COOL_EQUIP": "Cooling",
                "DESCRIPTION_HEAT_EQUIP": "Heating",
                "DISTRIBUTION": "UNKNOWN_DISTRIBUTION",
                "ECONOMIZER": "UNKNOWN_ECONOMIZER",
                "ECONOMIZER_EXCEPTION": "UNKNOWN_ECONOMIZER_EXCEPTION",
                "ELECTRIC_REHEAT": 0,
                "FAN_CONTROL": "UNKNOWN_FAN_CONTROL",
                "FAN_POWERED_VAV": 0,
                "FAN_SYSTEM_ID": null,
                "FAN_SYSTEM_KEY": "UNKNOWN_FAN_SYSTEM",
                "FAN_SYSTEM_OBJ_NUM": null,
                "FUEL": "ELECTRIC",
                "HEATING_EQUIPMENT": "HEAT_PUMP",
                "HEATING_EQUIP_CAPACITY": 39.3,
                "HEAT_PUMP": "WATER_LOOP_HEATPUMP",
                "HVAC_ID": 73976,
                "HYDRONIC_REHEAT": 0,
                "IS_HEATING_SYS_WEATHERIZED": null,
                "LIST_POSITION": 15,
                "PERIMETER_SYSTEM": 0,
                "PROP_COOLING_EQUIP_EFFICIENCY": 16.0,
                "PROP_HEATING_EQUIP_EFFICIENCY": 5.4,
                "QUANTITY": 1,
                "QUANTITY_COOL_EQUIP": 1,
                "QUANTITY_HEAT_EQUIP": 1,
                "REHEAT_RECOOL_COIL": 0,
                "RETURN_FAN_HP": 0.0,
                "STEAM_REHEAT": 0,
                "SUPPLY_FAN_HP": 0.0,
                "SUPPLY_STATIC_PRESSURE": 0.0,
                "SYSTEM_TYPE": null,
                "TOTAL_FAN_HP": 0.0,
                "VAR_AIR_BOX": 0,
                "VAR_AIR_VOL_MIXING_BOX": 0,
                "ZONE": "SINGLE_ZONE",
                "fanSystem": null,
                "isHeatingSysWeatherized": null
            },
            "3": {
                "ID": 182599,
                "ALT_EXEMPT_TYPE": null,
                "CONDENSER": "NO_CONDENSER",
                "CONST_VOL_MIXING_BOX": 0,
                "COOLING_EQUIPMENT": "HEAT_PUMP_EQUIPMENT",
                "COOLING_EQUIP_CAPACITY": 28.1,
                "DESCRIPTION": "HVAC System 4",
                "DESCRIPTION_COOL_EQUIP": "Cooling",
                "DESCRIPTION_HEAT_EQUIP": "Heating",
                "DISTRIBUTION": "UNKNOWN_DISTRIBUTION",
                "ECONOMIZER": "UNKNOWN_ECONOMIZER",
                "ECONOMIZER_EXCEPTION": "UNKNOWN_ECONOMIZER_EXCEPTION",
                "ELECTRIC_REHEAT": 0,
                "FAN_CONTROL": "UNKNOWN_FAN_CONTROL",
                "FAN_POWERED_VAV": 0,
                "FAN_SYSTEM_ID": null,
                "FAN_SYSTEM_KEY": "UNKNOWN_FAN_SYSTEM",
                "FAN_SYSTEM_OBJ_NUM": null,
                "FUEL": "ELECTRIC",
                "HEATING_EQUIPMENT": "HEAT_PUMP",
                "HEATING_EQUIP_CAPACITY": 31.5,
                "HEAT_PUMP": "WATER_LOOP_HEATPUMP",
                "HVAC_ID": 73976,
                "HYDRONIC_REHEAT": 0,
                "IS_HEATING_SYS_WEATHERIZED": null,
                "LIST_POSITION": 20,
                "PERIMETER_SYSTEM": 0,
                "PROP_COOLING_EQUIP_EFFICIENCY": 16.6,
                "PROP_HEATING_EQUIP_EFFICIENCY": 5.5,
                "QUANTITY": 1,
                "QUANTITY_COOL_EQUIP": 1,
                "QUANTITY_HEAT_EQUIP": 1,
                "REHEAT_RECOOL_COIL": 0,
                "RETURN_FAN_HP": 0.0,
                "STEAM_REHEAT": 0,
                "SUPPLY_FAN_HP": 0.0,
                "SUPPLY_STATIC_PRESSURE": 0.0,
                "SYSTEM_TYPE": null,
                "TOTAL_FAN_HP": 0.0,
                "VAR_AIR_BOX": 0,
                "VAR_AIR_VOL_MIXING_BOX": 0,
                "ZONE": "SINGLE_ZONE",
                "fanSystem": null,
                "isHeatingSysWeatherized": null
            },
            "4": {
                "ID": 182600,
                "ALT_EXEMPT_TYPE": null,
                "CONDENSER": "NO_CONDENSER",
                "CONST_VOL_MIXING_BOX": 0,
                "COOLING_EQUIPMENT": "HEAT_PUMP_EQUIPMENT",
                "COOLING_EQUIP_CAPACITY": 41.9,
                "DESCRIPTION": "HVAC System 5",
                "DESCRIPTION_COOL_EQUIP": "Cooling",
                "DESCRIPTION_HEAT_EQUIP": "Heating",
                "DISTRIBUTION": "UNKNOWN_DISTRIBUTION",
                "ECONOMIZER": "UNKNOWN_ECONOMIZER",
                "ECONOMIZER_EXCEPTION": "UNKNOWN_ECONOMIZER_EXCEPTION",
                "ELECTRIC_REHEAT": 0,
                "FAN_CONTROL": "UNKNOWN_FAN_CONTROL",
                "FAN_POWERED_VAV": 0,
                "FAN_SYSTEM_ID": null,
                "FAN_SYSTEM_KEY": "UNKNOWN_FAN_SYSTEM",
                "FAN_SYSTEM_OBJ_NUM": null,
                "FUEL": "ELECTRIC",
                "HEATING_EQUIPMENT": "HEAT_PUMP",
                "HEATING_EQUIP_CAPACITY": 48.7,
                "HEAT_PUMP": "WATER_LOOP_HEATPUMP",
                "HVAC_ID": 73976,
                "HYDRONIC_REHEAT": 0,
                "IS_HEATING_SYS_WEATHERIZED": null,
                "LIST_POSITION": 25,
                "PERIMETER_SYSTEM": 0,
                "PROP_COOLING_EQUIP_EFFICIENCY": 15.3,
                "PROP_HEATING_EQUIP_EFFICIENCY": 5.0,
                "QUANTITY": 1,
                "QUANTITY_COOL_EQUIP": 1,
                "QUANTITY_HEAT_EQUIP": 1,
                "REHEAT_RECOOL_COIL": 0,
                "RETURN_FAN_HP": 0.0,
                "STEAM_REHEAT": 0,
                "SUPPLY_FAN_HP": 0.0,
                "SUPPLY_STATIC_PRESSURE": 0.0,
                "SYSTEM_TYPE": null,
                "TOTAL_FAN_HP": 0.0,
                "VAR_AIR_BOX": 0,
                "VAR_AIR_VOL_MIXING_BOX": 0,
                "ZONE": "SINGLE_ZONE",
                "fanSystem": null,
                "isHeatingSysWeatherized": null
            },
            "5": {
                "ID": 182601,
                "ALT_EXEMPT_TYPE": null,
                "CONDENSER": "NO_CONDENSER",
                "CONST_VOL_MIXING_BOX": 0,
                "COOLING_EQUIPMENT": "HEAT_PUMP_EQUIPMENT",
                "COOLING_EQUIP_CAPACITY": 28.1,
                "DESCRIPTION": "HVAC System 6",
                "DESCRIPTION_COOL_EQUIP": "Cooling",
                "DESCRIPTION_HEAT_EQUIP": "Heating",
                "DISTRIBUTION": "UNKNOWN_DISTRIBUTION",
                "ECONOMIZER": "UNKNOWN_ECONOMIZER",
                "ECONOMIZER_EXCEPTION": "UNKNOWN_ECONOMIZER_EXCEPTION",
                "ELECTRIC_REHEAT": 0,
                "FAN_CONTROL": "UNKNOWN_FAN_CONTROL",
                "FAN_POWERED_VAV": 0,
                "FAN_SYSTEM_ID": null,
                "FAN_SYSTEM_KEY": "UNKNOWN_FAN_SYSTEM",
                "FAN_SYSTEM_OBJ_NUM": null,
                "FUEL": "ELECTRIC",
                "HEATING_EQUIPMENT": "HEAT_PUMP",
                "HEATING_EQUIP_CAPACITY": 31.5,
                "HEAT_PUMP": "WATER_LOOP_HEATPUMP",
                "HVAC_ID": 73976,
                "HYDRONIC_REHEAT": 0,
                "IS_HEATING_SYS_WEATHERIZED": null,
                "LIST_POSITION": 30,
                "PERIMETER_SYSTEM": 0,
                "PROP_COOLING_EQUIP_EFFICIENCY": 16.6,
                "PROP_HEATING_EQUIP_EFFICIENCY": 5.5,
                "QUANTITY": 1,
                "QUANTITY_COOL_EQUIP": 1,
                "QUANTITY_HEAT_EQUIP": 1,
                "REHEAT_RECOOL_COIL": 0,
                "RETURN_FAN_HP": 0.0,
                "STEAM_REHEAT": 0,
                "SUPPLY_FAN_HP": 0.0,
                "SUPPLY_STATIC_PRESSURE": 0.0,
                "SYSTEM_TYPE": null,
                "TOTAL_FAN_HP": 0.0,
                "VAR_AIR_BOX": 0,
                "VAR_AIR_VOL_MIXING_BOX": 0,
                "ZONE": "SINGLE_ZONE",
                "fanSystem": null,
                "isHeatingSysWeatherized": null
            },
            "6": {
                "ID": 182602,
                "ALT_EXEMPT_TYPE": null,
                "CONDENSER": "NO_CONDENSER",
                "CONST_VOL_MIXING_BOX": 0,
                "COOLING_EQUIPMENT": "HEAT_PUMP_EQUIPMENT",
                "COOLING_EQUIP_CAPACITY": 83.6,
                "DESCRIPTION": "HVAC System 7",
                "DESCRIPTION_COOL_EQUIP": "Cooling",
                "DESCRIPTION_HEAT_EQUIP": "Heating",
                "DISTRIBUTION": "UNKNOWN_DISTRIBUTION",
                "ECONOMIZER": "UNKNOWN_ECONOMIZER",
                "ECONOMIZER_EXCEPTION": "UNKNOWN_ECONOMIZER_EXCEPTION",
                "ELECTRIC_REHEAT": 0,
                "FAN_CONTROL": "UNKNOWN_FAN_CONTROL",
                "FAN_POWERED_VAV": 0,
                "FAN_SYSTEM_ID": null,
                "FAN_SYSTEM_KEY": "UNKNOWN_FAN_SYSTEM",
                "FAN_SYSTEM_OBJ_NUM": null,
                "FUEL": "ELECTRIC",
                "HEATING_EQUIPMENT": "HEAT_PUMP",
                "HEATING_EQUIP_CAPACITY": 97.7,
                "HEAT_PUMP": "WATER_LOOP_HEATPUMP",
                "HVAC_ID": 73976,
                "HYDRONIC_REHEAT": 0,
                "IS_HEATING_SYS_WEATHERIZED": null,
                "LIST_POSITION": 35,
                "PERIMETER_SYSTEM": 0,
                "PROP_COOLING_EQUIP_EFFICIENCY": 13.7,
                "PROP_HEATING_EQUIP_EFFICIENCY": 5.0,
                "QUANTITY": 1,
                "QUANTITY_COOL_EQUIP": 1,
                "QUANTITY_HEAT_EQUIP": 1,
                "REHEAT_RECOOL_COIL": 0,
                "RETURN_FAN_HP": 0.0,
                "STEAM_REHEAT": 0,
                "SUPPLY_FAN_HP": 0.0,
                "SUPPLY_STATIC_PRESSURE": 0.0,
                "SYSTEM_TYPE": null,
                "TOTAL_FAN_HP": 0.0,
                "VAR_AIR_BOX": 0,
                "VAR_AIR_VOL_MIXING_BOX": 0,
                "ZONE": "SINGLE_ZONE",
                "fanSystem": null,
                "isHeatingSysWeatherized": null
            }
        },
        "fan_systems": null
    }
}