{
    "building_name": "cbecs9",
    "building_area_type": "Office",
    "year_built": 1980,
    "ashrae_climate_zone": "2A",
    "epw_file": "USA_FL_Tampa-MacDill.AFB.747880_TMY3.epw",
    "gross_conditioned_area(ft2)": 37500,
    "number_of_floor": 1,
    "floor_to_ceil_height(ft)": 12,
    "south_gross_wall_area(ft2)": 2946.726997874082,
    "east_gross_wall_area(ft2)": 1832.5416653445786,
    "north_gross_wall_area(ft2)": 2946.726997874082,
    "west_gross_wall_area(ft2)": 1832.5416653445786,
    "south_window_area(ft2)": 530.4108596173347,
    "east_window_area(ft2)": 329.85749976202413,
    "north_window_area(ft2)": 530.4108596173347,
    "west_window_area(ft2)": 329.85749976202413,
    "wall_type": "Mass",
    "wall_u_factor(Btu/h-ft2-F)": 0.375,
    "roof_type": "Attic and Other",
    "roof_u_factor(Btu/h-ft2-F)": 0.056,
    "window_U_factor(Btu/h-ft2-F)": 1.22,
    "window_shgc": 0.25,
    "people_density(people/1000ft2)": 0.6666666666666666,
    "lpd(W/ft2)": 1.8,
    "plug_load_density(W/ft2)": 0.8161189591078067,
    "Infiltration_rate(cfm/ft2)": 0.75,
    "weekly_occupied_hours(hr/wk)": 68,
    "number_days_open_workday": 5,
    "number_days_open_weekend": 2,
    "heating_system_type": "Gas",
    "cooling_system_type": "SingleSpeedDX",
    "ventilation_rate_per_person(cfm/person)": 5.0,
    "ventilation_rate_per_area(cfm/ft2)": 0.06,
    "economizer_used": "Yes",
    "heat_recovery_used": "No"
}