{
    "idf_obj_types_for_osstd_use": [
        "Zone",
        "SizingPeriod:DesignDay",
        "Building",
        "GlobalGeometryRules"
    ],
    "excluded_osstd_hvac_obj_types_file_path": "../resources/exc_osstd_hvac_objtypes_meta.json",
    "replace_osstd_hvac_schedules_refs_file_path": "../resources/replace_osstd_hvac_schedules_refs.json",
    "hvac_intermediate_folder_name": "hvac_dev",
    "considered_hvac_types": [
        "PSZ_Gas_SingleSpeedDX",
        "PSZ_Electric_SingleSpeedDX",
        "VAV_HotWater_ChilledWater",
        "Gas_Heating_Ventilation",
        "PTHP",
        "PTAC_Electric",
        "PTAC_Gas",
        "Electric_Heating_Ventilation",
        "PSZ_HP",
        "PVAV_Gas_ElectricReheat",
        "Fan_Coil",
        "VAV_PFP",
        "PVAV_Gas_GasReheat"
    ]
}